py_opencommit/__init__.py
py_opencommit/cli.py
py_opencommit/commands/__init__.py
py_opencommit/commands/commit.py
py_opencommit/commands/config.py
py_opencommit/commands/githook.py
py_opencommit/engine/__init__.py
py_opencommit/engine/base.py
py_opencommit/engine/openai.py
py_opencommit/i18n/__init__.py
py_opencommit/migrations/__init__.py
py_opencommit/migrations/migrate_00_initialize_config.py
py_opencommit/modules/__init__.py
py_opencommit/modules/commitlint/__init__.py
py_opencommit/modules/commitlint/prompts.py
py_opencommit/utils/__init__.py
py_opencommit/utils/git.py
py_opencommit/utils/pydantic_config.py
py_opencommit/utils/token_count.py
py_opencommit-0.1.1.dist-info/licenses/LICENSE
py_opencommit-0.1.1.dist-info/METADATA
py_opencommit-0.1.1.dist-info/WHEEL
py_opencommit-0.1.1.dist-info/entry_points.txt
py_opencommit-0.1.1.dist-info/top_level.txt
py_opencommit-0.1.1.dist-info/RECORD
