Metadata-Version: 2.4
Name: py-opencommit
Version: 0.1.1
Summary: AI-powered commit message generator
Author: OpenCommit Team, Ariel Frischer
License: MIT
Classifier: Programming Language :: Python :: 3
Classifier: License :: OSI Approved :: MIT License
Classifier: Operating System :: OS Independent
Requires-Python: >=3.10
License-File: LICENSE
Requires-Dist: litellm>=1.0.0
Requires-Dist: requests>=2.28.0
Requires-Dist: httpx>=0.24.0
Requires-Dist: rich>=13.0.0
Requires-Dist: python-dotenv>=1.0.0
Requires-Dist: configparser>=5.3.0
Requires-Dist: inquirerpy>=0.3.4
Requires-Dist: pyyaml>=6.0
Requires-Dist: pygithub>=1.58.0
Requires-Dist: click>=8.1.3
Requires-Dist: colorama>=0.4.6
Requires-Dist: gitpython>=3.1.30
Provides-Extra: ai
Requires-Dist: openai>=1.0.0; extra == "ai"
Requires-Dist: anthropic>=0.5.0; extra == "ai"
Requires-Dist: google-generativeai>=0.2.0; extra == "ai"
Requires-Dist: mistralai>=0.0.1; extra == "ai"
Requires-Dist: groq>=0.3.0; extra == "ai"
Provides-Extra: dev
Requires-Dist: pytest>=7.3.1; extra == "dev"
Requires-Dist: pytest-cov>=4.1.0; extra == "dev"
Requires-Dist: pytest-console-scripts>=1.4.0; extra == "dev"
Requires-Dist: black>=23.3.0; extra == "dev"
Requires-Dist: flake8>=6.0.0; extra == "dev"
Requires-Dist: pylint>=2.17.0; extra == "dev"
Requires-Dist: mypy>=1.3.0; extra == "dev"
Requires-Dist: isort>=5.12.0; extra == "dev"
Dynamic: license-file
